[
  {
    "title": "대부업등 감독규정 시행세칙",
    "date": "2025-07-22",
    "source": "금융감독원",
    "url": "https://www.fss.or.kr/fss/job/lrgRegItnInfo/view.do?lrgClsfcNo=USR000000000000000190&menuNo=200488&pageIndex=1",
    "type": "최근 제개정 정보",
    "attachments": [
      {
        "filename": "대부업등 감독규정 시행세칙 일부 개정안 신구조문대비표_F_12282362417451559.pdf",
        "path": "data/pdf/대부업등 감독규정 시행세칙 일부 개정안 신구조문대비표_F_12282362417451559.pdf"
      },
      {
        "filename": "별첨_금융위 등록 대부업자 업무보고서(별지 제8호)_F_12282362455722628.pdf",
        "path": "data/pdf/별첨_금융위 등록 대부업자 업무보고서(별지 제8호)_F_12282362455722628.pdf"
      }
    ],
    "text": ""
  },
  {
    "title": "금융투자업규정시행세칙",
    "date": "2025-07-01",
    "source": "금융감독원",
    "url": "https://www.fss.or.kr/fss/job/lrgRegItnInfo/view.do?lrgClsfcNo=USR000000000000000189&menuNo=200488&pageIndex=1",
    "type": "최근 제개정 정보",
    "attachments": [
      {
        "filename": "금융투자업규정시행세칙 일부개정안(홈페이지 게시용)_10457976821555516.pdf",
        "path": "data/pdf/금융투자업규정시행세칙 일부개정안(홈페이지 게시용)_10457976821555516.pdf"
      }
    ],
    "text": ""
  },
  {
    "title": "보험업감독업무시행세칙",
    "date": "2025-06-30",
    "source": "금융감독원",
    "url": "https://www.fss.or.kr/fss/job/lrgRegItnInfo/view.do?lrgClsfcNo=USR000000000000000187&menuNo=200488&pageIndex=1",
    "type": "최근 제개정 정보",
    "attachments": [
      {
        "filename": "250630 보험업감독업무시행세칙 일부 개정 신구조문 대비표_10191883429358141.pdf",
        "path": "data/pdf/250630 보험업감독업무시행세칙 일부 개정 신구조문 대비표_10191883429358141.pdf"
      }
    ],
    "text": ""
  },
  {
    "title": "금융투자업규정시행세칙",
    "date": "2025-06-27",
    "source": "금융감독원",
    "url": "https://www.fss.or.kr/fss/job/lrgRegItnInfo/view.do?lrgClsfcNo=USR000000000000000188&menuNo=200488&pageIndex=1",
    "type": "최근 제개정 정보",
    "attachments": [
      {
        "filename": "「금융투자업규정시행세칙」 일부 개정안(홈페이지 게시)_10456223111889829.pdf",
        "path": "data/pdf/「금융투자업규정시행세칙」 일부 개정안(홈페이지 게시)_10456223111889829.pdf"
      }
    ],
    "text": ""
  },
  {
    "title": "은행업감독업무시행세칙 및 금융투자업규정시행세칙",
    "date": "2025-06-25",
    "source": "금융감독원",
    "url": "https://www.fss.or.kr/fss/job/lrgRegItnInfo/view.do?lrgClsfcNo=USR000000000000000186&menuNo=200488&pageIndex=1",
    "type": "최근 제개정 정보",
    "attachments": [
      {
        "filename": "은행업감독업무시행세칙 등 개정안_신구조문 대비표_10024033598228320.pdf",
        "path": "data/pdf/은행업감독업무시행세칙 등 개정안_신구조문 대비표_10024033598228320.pdf"
      },
      {
        "filename": "(별첨1) (외국환업무 현황보고서) (19) 만기별 외화자금 유출입 현황(FW031)_10024033612281222.pdf",
        "path": "data/pdf/(별첨1) (외국환업무 현황보고서) (19) 만기별 외화자금 유출입 현황(FW031)_10024033612281222.pdf"
      },
      {
        "filename": "(별첨2) (외국환업무 현황보고서) (20) 일자별 외화자금 유출입 현황(FW030)_10024033617467745.pdf",
        "path": "data/pdf/(별첨2) (외국환업무 현황보고서) (20) 일자별 외화자금 유출입 현황(FW030)_10024033617467745.pdf"
      }
    ],
    "text": ""
  },
  {
    "title": "보험업감독업무시행세칙",
    "date": "2025-06-11",
    "source": "금융감독원",
    "url": "https://www.fss.or.kr/fss/job/lrgRegItnInfo/view.do?lrgClsfcNo=USR000000000000000185&menuNo=200488&pageIndex=1",
    "type": "최근 제개정 정보",
    "attachments": [
      {
        "filename": "250611_보험업감독업무시행세칙 일부 개정안 신구조문 대비표_8824769370444906.pdf",
        "path": "data/pdf/250611_보험업감독업무시행세칙 일부 개정안 신구조문 대비표_8824769370444906.pdf"
      },
      {
        "filename": "(별첨1) [별지26] 업무보고서 일부 개정서식_8824769385381449.pdf",
        "path": "data/pdf/(별첨1) [별지26] 업무보고서 일부 개정서식_8824769385381449.pdf"
      },
      {
        "filename": "(별첨2) [별지64] 자본조달 수단 발행 및 상환 신고서(제5-7조의4 관련)_8824769405008302.pdf",
        "path": "data/pdf/(별첨2) [별지64] 자본조달 수단 발행 및 상환 신고서(제5-7조의4 관련)_8824769405008302.pdf"
      }
    ],
    "text": ""
  },
  {
    "title": "증권의 발행 및 공시 등에 관한 규정 시행세칙",
    "date": "2025-05-29",
    "source": "금융감독원",
    "url": "https://www.fss.or.kr/fss/job/lrgRegItnInfo/view.do?lrgClsfcNo=USR000000000000000184&menuNo=200488&pageIndex=1",
    "type": "최근 제개정 정보",
    "attachments": [
      {
        "filename": "증권의 발행 및 공시 등에 관한 규정 시행세칙 일부 개정안_8031340584740568.pdf",
        "path": "data/pdf/증권의 발행 및 공시 등에 관한 규정 시행세칙 일부 개정안_8031340584740568.pdf"
      }
    ],
    "text": ""
  },
  {
    "title": "외부감사 및 회계 등에 관한 규정 시행세칙",
    "date": "2025-05-20",
    "source": "금융감독원",
    "url": "https://www.fss.or.kr/fss/job/lrgRegItnInfo/view.do?lrgClsfcNo=USR000000000000000183&menuNo=200488&pageIndex=1",
    "type": "최근 제개정 정보",
    "attachments": [
      {
        "filename": "외부감사 및 회계 등에 관한 규정 시행세칙 일부 개정(안)_홈페이지 등록_6979988676629842.pdf",
        "path": "data/pdf/외부감사 및 회계 등에 관한 규정 시행세칙 일부 개정(안)_홈페이지 등록_6979988676629842.pdf"
      }
    ],
    "text": ""
  },
  {
    "title": "은행업감독업무시행세칙",
    "date": "2025-05-16",
    "source": "금융감독원",
    "url": "https://www.fss.or.kr/fss/job/lrgRegItnInfo/view.do?lrgClsfcNo=USR000000000000000182&menuNo=200488&pageIndex=1",
    "type": "최근 제개정 정보",
    "attachments": [
      {
        "filename": "(본문) 은행업감독업무시행세칙 개정안_신구조문 대비표_6568123893519221.pdf",
        "path": "data/pdf/(본문) 은행업감독업무시행세칙 개정안_신구조문 대비표_6568123893519221.pdf"
      }
    ],
    "text": ""
  },
  {
    "title": "금융지주회사감독규정시행세칙",
    "date": "2025-05-16",
    "source": "금융감독원",
    "url": "https://www.fss.or.kr/fss/job/lrgRegItnInfo/view.do?lrgClsfcNo=USR000000000000000181&menuNo=200488&pageIndex=1",
    "type": "최근 제개정 정보",
    "attachments": [
      {
        "filename": "(본문) 금융지주회사감독규정시행세칙 개정안_신구조문대비표_6567995135748053.pdf",
        "path": "data/pdf/(본문) 금융지주회사감독규정시행세칙 개정안_신구조문대비표_6567995135748053.pdf"
      },
      {
        "filename": "(별첨) 별지 제18호 지주 업무보고서 개정(안)_6567995152620969.pdf",
        "path": "data/pdf/(별첨) 별지 제18호 지주 업무보고서 개정(안)_6567995152620969.pdf"
      }
    ],
    "text": ""
  },
  {
    "title": "금융분쟁조정세칙",
    "date": "2025-04-04",
    "source": "금융감독원",
    "url": "https://www.fss.or.kr/fss/job/lrgRegItnInfo/view.do?lrgClsfcNo=USR000000000000000180&menuNo=200488&pageIndex=2",
    "type": "최근 제개정 정보",
    "attachments": [
      {
        "filename": "금융분쟁조정세칙 일부개정안(2025.4.4.)_2937629587598730.pdf",
        "path": "data/pdf/금융분쟁조정세칙 일부개정안(2025.4.4.)_2937629587598730.pdf"
      },
      {
        "filename": "금융분쟁조정세칙 일부개정안(2025.4.4.)_2937629590627733.pdf",
        "path": "data/pdf/금융분쟁조정세칙 일부개정안(2025.4.4.)_2937629590627733.pdf"
      },
      {
        "filename": "금융분쟁조정세칙(금융감독원세칙)(20250404)_2938822073488800.pdf",
        "path": "data/pdf/금융분쟁조정세칙(금융감독원세칙)(20250404)_2938822073488800.pdf"
      }
    ],
    "text": ""
  },
  {
    "title": "보험업감독업무시행세칙",
    "date": "2025-03-31",
    "source": "금융감독원",
    "url": "https://www.fss.or.kr/fss/job/lrgRegItnInfo/view.do?lrgClsfcNo=USR000000000000000179&menuNo=200488&pageIndex=2",
    "type": "최근 제개정 정보",
    "attachments": [
      {
        "filename": "보험업감독업무시행세칙 신구조문대비표_2585969355272976.pdf",
        "path": "data/pdf/보험업감독업무시행세칙 신구조문대비표_2585969355272976.pdf"
      },
      {
        "filename": "(별첨) [별지26] 업무보고서 일부 개정서식_2585969362735981.pdf",
        "path": "data/pdf/(별첨) [별지26] 업무보고서 일부 개정서식_2585969362735981.pdf"
      }
    ],
    "text": ""
  },
  {
    "title": "퇴직연금감독규정시행세칙",
    "date": "2025-03-24",
    "source": "금융감독원",
    "url": "https://www.fss.or.kr/fss/job/lrgRegItnInfo/view.do?lrgClsfcNo=USR000000000000000178&menuNo=200488&pageIndex=2",
    "type": "최근 제개정 정보",
    "attachments": [
      {
        "filename": "1. 개정내용_퇴직연금감독규정 시행세칙 일부개정안(20250401)_2241952356418436.pdf",
        "path": "data/pdf/1. 개정내용_퇴직연금감독규정 시행세칙 일부개정안(20250401)_2241952356418436.pdf"
      },
      {
        "filename": "1. 개정내용 업무보고서 개정 서식_2241952369953686.pdf",
        "path": "data/pdf/1. 개정내용 업무보고서 개정 서식_2241952369953686.pdf"
      },
      {
        "filename": "2. 개정전문_퇴직연금감독규정시행세칙(금융감독원세칙, 20250401)_2241952373082257.pdf",
        "path": "data/pdf/2. 개정전문_퇴직연금감독규정시행세칙(금융감독원세칙, 20250401)_2241952373082257.pdf"
      },
      {
        "filename": "2. 개정전문_[별표 1] 비교공시항목 작성기준(제7조 관련)(20250401)_2241952379398634.pdf",
        "path": "data/pdf/2. 개정전문_[별표 1] 비교공시항목 작성기준(제7조 관련)(20250401)_2241952379398634.pdf"
      },
      {
        "filename": "2. 개정전문_[별지 1] 퇴직연금 영업(업무)보고서(20250401)_2241952384383959.pdf",
        "path": "data/pdf/2. 개정전문_[별지 1] 퇴직연금 영업(업무)보고서(20250401)_2241952384383959.pdf"
      }
    ],
    "text": ""
  },
  {
    "title": "금융투자업규정시행세칙",
    "date": "2025-03-13",
    "source": "금융감독원",
    "url": "https://www.fss.or.kr/fss/job/lrgRegItnInfo/view.do?lrgClsfcNo=USR000000000000000177&menuNo=200488&pageIndex=2",
    "type": "최근 제개정 정보",
    "attachments": [
      {
        "filename": "금융투자업규정시행세칙(규제영향분석서)_20250113_1028845046189752.pdf",
        "path": "data/pdf/금융투자업규정시행세칙(규제영향분석서)_20250113_1028845046189752.pdf"
      },
      {
        "filename": "250313_F 금융투자업규정시행세칙 개정안 신구조문대비표 (홈페이지게시)_1028845057492663.pdf",
        "path": "data/pdf/250313_F 금융투자업규정시행세칙 개정안 신구조문대비표 (홈페이지게시)_1028845057492663.pdf"
      },
      {
        "filename": "[별표 35] 공매도 내부통제 구축 기준_1028845071663837.pdf",
        "path": "data/pdf/[별표 35] 공매도 내부통제 구축 기준_1028845071663837.pdf"
      },
      {
        "filename": "[별표 36] 무차입공매도 방지조치 이행여부 점검기준(제4-6조제1항 관련)_1028845074901834.pdf",
        "path": "data/pdf/[별표 36] 무차입공매도 방지조치 이행여부 점검기준(제4-6조제1항 관련)_1028845074901834.pdf"
      },
      {
        "filename": "[별책서식1_38의4호] 무차입공매도 방지조치 확인결과 보고서_1028845080658037.pdf",
        "path": "data/pdf/[별책서식1_38의4호] 무차입공매도 방지조치 확인결과 보고서_1028845080658037.pdf"
      }
    ],
    "text": ""
  },
  {
    "title": "은행업감독업무시행세칙",
    "date": "2025-02-27",
    "source": "금융감독원",
    "url": "https://www.fss.or.kr/fss/job/lrgRegItnInfo/view.do?lrgClsfcNo=USR000000000000000175&menuNo=200488&pageIndex=2",
    "type": "최근 제개정 정보",
    "attachments": [
      {
        "filename": "은행업감독업무시행세칙 개정(안)(25.2.27. 시행)(송부)_7683140007567332.pdf",
        "path": "data/pdf/은행업감독업무시행세칙 개정(안)(25.2.27. 시행)(송부)_7683140007567332.pdf"
      },
      {
        "filename": "(별첨) 별책서식 제57호 은행 업무보고서 개정(안)_7683140013539689.pdf",
        "path": "data/pdf/(별첨) 별책서식 제57호 은행 업무보고서 개정(안)_7683140013539689.pdf"
      }
    ],
    "text": ""
  },
  {
    "title": "보험업감독업무시행세칙",
    "date": "2025-02-12",
    "source": "금융감독원",
    "url": "https://www.fss.or.kr/fss/job/lrgRegItnInfo/view.do?lrgClsfcNo=USR000000000000000174&menuNo=200488&pageIndex=2",
    "type": "최근 제개정 정보",
    "attachments": [
      {
        "filename": "(붙임) 보험업감독업무시행세칙 일부개정(안)_6393117145976444.pdf",
        "path": "data/pdf/(붙임) 보험업감독업무시행세칙 일부개정(안)_6393117145976444.pdf"
      },
      {
        "filename": "(별첨) 별지제26호_업무보고서_6393117160254022.pdf",
        "path": "data/pdf/(별첨) 별지제26호_업무보고서_6393117160254022.pdf"
      }
    ],
    "text": ""
  },
  {
    "title": "전자금융감독규정시행세칙",
    "date": "2025-02-03",
    "source": "금융감독원",
    "url": "https://www.fss.or.kr/fss/job/lrgRegItnInfo/view.do?lrgClsfcNo=USR000000000000000173&menuNo=200488&pageIndex=2",
    "type": "최근 제개정 정보",
    "attachments": [
      {
        "filename": "전자금융감독규정시행세칙 일부개정 신구조문대비표_5876332837227293.pdf",
        "path": "data/pdf/전자금융감독규정시행세칙 일부개정 신구조문대비표_5876332837227293.pdf"
      }
    ],
    "text": ""
  },
  {
    "title": "상호저축은행업감독업무시행세칙",
    "date": "2025-01-15",
    "source": "금융감독원",
    "url": "https://www.fss.or.kr/fss/job/lrgRegItnInfo/view.do?lrgClsfcNo=USR000000000000000172&menuNo=200488&pageIndex=2",
    "type": "최근 제개정 정보",
    "attachments": [
      {
        "filename": "(홈페이지 공개) 상호저축은행업감독업무시행세칙 일부 개정_3941451188925463.pdf",
        "path": "data/pdf/(홈페이지 공개) 상호저축은행업감독업무시행세칙 일부 개정_3941451188925463.pdf"
      }
    ],
    "text": ""
  },
  {
    "title": "금융기관 검사 및 제재에 관한 규정 시행세칙",
    "date": "2025-01-08",
    "source": "금융감독원",
    "url": "https://www.fss.or.kr/fss/job/lrgRegItnInfo/view.do?lrgClsfcNo=USR000000000000000167&menuNo=200488&pageIndex=2",
    "type": "최근 제개정 정보",
    "attachments": [
      {
        "filename": "금융기관 검사 및 제재에 관한 규정 시행세칙 일부 개정안(25.1.8. 시행)_홈페이지_3528528035200199.pdf",
        "path": "data/pdf/금융기관 검사 및 제재에 관한 규정 시행세칙 일부 개정안(25.1.8. 시행)_홈페이지_3528528035200199.pdf"
      }
    ],
    "text": ""
  }
]